flownets/BlocksAndLayers.py
flownets/UNets.py
flownets/__init__.py
flownets/version.py
flownets-0.0.3.dist-info/licenses/LICENSE
flownets-0.0.3.dist-info/METADATA
flownets-0.0.3.dist-info/WHEEL
flownets-0.0.3.dist-info/top_level.txt
flownets-0.0.3.dist-info/RECORD
