Metadata-Version: 2.4
Name: flownets
Version: 0.0.3
Summary: A new beginning for my models :)
Home-page: https://github.com/TommyGiak/FlowNets
Author: Tommaso Giacometti
Author-email: tommaso.giak@gmail.com
License: MIT
Classifier: Programming Language :: Python :: 3
Classifier: License :: OSI Approved :: MIT License
Classifier: Operating System :: OS Independent
Requires-Python: >=3.8
License-File: LICENSE
Requires-Dist: numpy
Requires-Dist: torch
Requires-Dist: einops
Dynamic: author
Dynamic: author-email
Dynamic: classifier
Dynamic: description
Dynamic: description-content-type
Dynamic: home-page
Dynamic: license
Dynamic: license-file
Dynamic: requires-dist
Dynamic: requires-python
Dynamic: summary
